{
  "id": 274763162,
  "master_id": 274763162,
  "sku": "2625227578806",
  "name": "Lịch Sử Các Lý Thuyết Truyền Thông",
  "url_key": "lich-su-cac-ly-thuyet-truyen-thong-p274763162",
  "url_path": "lich-su-cac-ly-thuyet-truyen-thong-p274763162.html?spid=274763163",
  "short_url": "https://tiki.vn/product-p274763162.html?spid=274763163",
  "type": "simple",
  "book_cover": null,
  "short_description": "LỊCH SỬ CÁC LÝ THUYẾT TRUYỀN THÔNG (Histoire des théories de la communication)Từ lâu, truyền thông (communication) vốn là một khái niệm bao hàm rất nhiều ý nghĩa khác nhau. Giờ đây, sự phát triển của...",
  "price": 141000,
  "list_price": 175000,
  "original_price": 175000,
  "badges": [
    {
      "code": "has_book_preview",
      "text": "Đọc thử"
    },
    {
      "code": "new_pdp",
      "text": "v1"
    }
  ],
  "badges_new": [
    {
      "placement": "left_brand",
      "code": "is_authentic",
      "type": "is_authentic",
      "index": 4,
      "icon": "https://salt.tikicdn.com/ts/upload/d7/56/04/b93b8c666e13f49971483596ef14800f.png",
      "icon_width": 89,
      "icon_height": 20,
      "text_color": null,
      "background_color": null,
      "href": null,
      "text": null
    },
    {
      "placement": "right_authentic",
      "code": "return_policy",
      "type": "return_policy",
      "index": 3,
      "icon": "https://salt.tikicdn.com/ts/ta/b1/3f/4e/cc3d0a2dd751a7b06dd97d868d6afa56.png",
      "icon_width": 114,
      "icon_height": 20,
      "text_color": null,
      "background_color": null,
      "href": null,
      "text": null
    }
  ],
  "badges_v3": [
    {
      "placement": "pdp_badge",
      "code": "return_policy",
      "type": "pdp_icon_badge",
      "index": 3,
      "icon": "https://salt.tikicdn.com/ts/ta/b1/3f/4e/cc3d0a2dd751a7b06dd97d868d6afa56.png",
      "icon_width": 114,
      "icon_height": 20,
      "text_color": null,
      "background_color": null,
      "href": null,
      "text": null
    },
    {
      "placement": "pdp_badge",
      "code": "is_authentic",
      "type": "pdp_icon_badge",
      "index": 4,
      "icon": "https://salt.tikicdn.com/ts/upload/d7/56/04/b93b8c666e13f49971483596ef14800f.png",
      "icon_width": 89,
      "icon_height": 20,
      "text_color": null,
      "background_color": null,
      "href": null,
      "text": null
    }
  ],
  "tracking_info": {
    "amplitude": {
      "is_authentic": true,
      "is_freeship_xtra": false,
      "is_hero": false,
      "is_top_brand": false,
      "return_reason": "any_reason"
    }
  },
  "discount": 34000,
  "discount_rate": 19,
  "rating_average": 5,
  "review_count": 5,
  "review_text": "(5)",
  "favourite_count": 0,
  "thumbnail_url": "https://salt.tikicdn.com/cache/280x280/ts/product/49/e2/03/6d3b71e2879bab68f796c9166bc6f14a.jpg",
  "has_ebook": false,
  "inventory_status": "available",
  "inventory_type": "instock",
  "productset_group_name": "",
  "is_fresh": false,
  "seller": null,
  "is_flower": false,
  "has_buynow": true,
  "is_gift_card": false,
  "salable_type": null,
  "data_version": 3300,
  "day_ago_created": 383,
  "all_time_quantity_sold": 55,
  "meta_title": "",
  "meta_description": "",
  "meta_keywords": "",
  "is_baby_milk": false,
  "is_acoholic_drink": false,
  "description": "<p><strong>LỊCH SỬ CÁC LÝ THUYẾT TRUYỀN THÔNG </strong><br /><strong>(Histoire des théories de la communication)</strong></p>\n<p>Từ lâu, truyền thông (communication) vốn là một khái niệm bao hàm rất nhiều ý nghĩa khác nhau. Giờ đây, sự phát triển của công nghệ và sự chuyên nghiệp hóa các hoạt động càng làm tăng thêm những nội hàm mới cho thuật ngữ vốn đa nghĩa này, đặc biệt là trong thời đại mà người ta xem truyền thông như một biểu trưng của các xã hội trong thiên niên kỷ thứ ba.</p>\n<p>Nằm tại giao điểm của nhiều ngành khoa học, các quá trình truyền thông đã thu hút sự quan tâm của nhiều ngành khoa học hết sức đa dạng như triết học, lịch sử, địa lý, tâm lý học, xã hội học, dân tộc học, kinh tế học, chính trị học, sinh học, điều khiển học, và các bộ môn khoa học tri nhận (sciences cognitives). Trong quá trình hình thành, lĩnh vực khoa học xã hội chuyên biệt này vẫn không ngừng bị ám ảnh bởi vấn đề về tính chính đáng khoa học của mình. Điều này đã thúc đẩy bộ môn này đi tìm kiếm những mô hình khoa học, bằng cách tiếp thu những lược đồ thích hợp vốn thuộc về các ngành khoa học tự nhiên thông qua các phương pháp loại suy.</p>\n<p>Công trình này ra đời nhằm mục đích phân tích và giải thích sự đa diện và sự bùng nổ của phạm vi nghiên cứu về truyền thông, mà về mặt lịch sử, đã luôn nằm trong sự tranh chấp giữa các hệ thống vật thể và các hệ thống phi vật thể, giữa bình diện sinh học và bình diện xã hội, giữa tự nhiên và văn hóa, giữa các công cụ kỹ thuật và ngôn từ, giữa kinh tế và văn hóa, giữa các nhãn giới vi mô và vĩ mô, giữa ngôi làng và toàn cầu, giữa tác nhân và hệ thống, giữa cá nhân và xã hội, giữa tự do ý chí và các xu hướng quyết định luận xã hội. Lịch sử các lý thuyết về truyền thông chính là lịch sử của những sự giằng co ấy và của những nỗ lực khác nhau nhằm liên kết hoặc không liên kết những cái vế vốn thường xuất hiện dưới dạng lưỡng phân, và đối lập nhị phân hơn là dưới các cấp độ phân tích. Trong các bối cảnh lịch sử khác nhau, bằng những lối diễn đạt khác nhau, những sự căng thẳng và đối kháng này, vốn là khởi nguồn của những quan điểm độc tôn, đã không ngừng diễn ra trong một thời gian dài, và dẫn đến sự hình thành của các trường phái, các trào lưu và các xu hướng.</p>\n<p>Chính tình trạng dai dẳng căn bản ấy làm cho bất cứ lối tiếp cận nào quá thiên về tính chất biên niên đối với lịch sử các lý thuyết cũng đều trở nên không có giá trị. Quá trình lúc tiến lúc thoái của các lối đặt vấn đề khác nhau không cho phép chúng ta hình dung diễn trình này theo kiểu tuyến tính. Mặc dù công trình này đi theo một nguyên tắc sắp xếp tối thiểu theo thứ tự xuất hiện của các trường phái, các trào lưu hay các xu hướng, nhưng nó vẫn muốn nhấn mạnh đến tính chất trở đi trở lại của các lối đặt vấn đề nghiên cứu. Có những cuộc tranh luận xa xưa về các đối tượng và các chiến lược nghiên cứu mà trong một thời gian dài người ta tưởng là đã được giải quyết xong, đột nhiên nảy sinh trở lại, đặt lại vấn đề về các phương thức khả niệm và về các quy chế chân lý vốn từng thống trị trong nhiều thập niên. Một trong những ví dụ minh họa rõ nét nhất là sự xuất hiện trở lại mạnh mẽ của nhãn quan dân tộc học vào những năm 1980, khi mà những quan điểm toàn quy [totalisantes] về xã hội lâm vào sự khủng hoảng.</p>\n<p>Nếu ý niệm về truyền thông vẫn còn gây ra vấn đề thì ý niệm về lý thuyết truyền thông cũng thế. Ý niệm này cũng là một trong những nhân tố gây nên sự chia rẽ. Trước hết, vị thế và định nghĩa về lý thuyết, cũng giống như trong nhiều ngành khoa học về con người và về xã hội, được hiểu một cách khác hẳn giữa trường phái này với trường phái khác, giữa phái khoa học luận này với phái khoa học luận khác. Hơn nữa, việc gọi tên các “trường phái” cũng có thể gây ra ngộ nhận. Thực vậy, một trường phái có thể dung chứa nhiều nhóm khác nhau và khó mà có được sự đồng nhất mà cái tên của nó có vẻ nhắm đến. Cuối cùng, diễn ngôn về truyền thông thường được nâng lên hàng lý thuyết tổng quát mà không cần biện luận. Những câu nói bóng bẩy của Marshall McLuhan có thể đứng bên cạnh bộ máy khái niệm triết học nặng nề của Jürgen Habermas mà người ta khó có thể nói ai là người đã làm đảo lộn các quan điểm về môi trường công nghệ.</p>\n<p>Những học thuyết mang tính thời thượng và những ý tưởng “mì ăn liền” xuất hiện nhất thời được người ta xem như là những lược đồ giải thích chung cuộc, những bài học hạng bậc thầy, mà không hề quan tâm tới những điều khám phá được qua một quá trình tích lũy lâu dài, đầy mâu thuẫn và mang tính chất đa ngành, cũng như không quan tâm tới những tri thức trong lĩnh vực này, và vì thế càng làm tăng thêm ấn tượng về tính phù phiếm của đối tượng nghiên cứu này. Có lẽ rõ nét nhất trong lĩnh vực khoa học này hơn là trong những lĩnh vực khoa học khác, người ta dễ rơi vào ảo tưởng nghĩ rằng mình có thể xóa bỏ sạch trơn quá trình trầm tích ấy, và rằng trong ngành khoa học này, khác với các ngành khác, tất cả đều cần được sáng tạo từ đầu.</p><p>Giá sản phẩm trên Tiki đã bao gồm thuế theo luật hiện hành. Bên cạnh đó, tuỳ vào loại sản phẩm, hình thức và địa chỉ giao hàng mà có thể phát sinh thêm chi phí khác như phí vận chuyển, phụ phí hàng cồng kềnh, thuế nhập khẩu (đối với đơn hàng giao từ nước ngoài có giá trị trên 1 triệu đồng).....</p>",
  "images": [
    {
      "base_url": "https://salt.tikicdn.com/ts/product/49/e2/03/6d3b71e2879bab68f796c9166bc6f14a.jpg",
      "is_gallery": true,
      "label": null,
      "large_url": "https://salt.tikicdn.com/cache/w1200/ts/product/49/e2/03/6d3b71e2879bab68f796c9166bc6f14a.jpg",
      "medium_url": "https://salt.tikicdn.com/cache/w300/ts/product/49/e2/03/6d3b71e2879bab68f796c9166bc6f14a.jpg",
      "position": null,
      "small_url": "https://salt.tikicdn.com/cache/200x280/ts/product/49/e2/03/6d3b71e2879bab68f796c9166bc6f14a.jpg",
      "thumbnail_url": "https://salt.tikicdn.com/cache/200x280/ts/product/49/e2/03/6d3b71e2879bab68f796c9166bc6f14a.jpg"
    },
    {
      "base_url": "https://salt.tikicdn.com/ts/product/22/66/65/91aee3e77757f106ac2055334a4b6521.jpg",
      "is_gallery": true,
      "label": null,
      "large_url": "https://salt.tikicdn.com/cache/w1200/ts/product/22/66/65/91aee3e77757f106ac2055334a4b6521.jpg",
      "medium_url": "https://salt.tikicdn.com/cache/w300/ts/product/22/66/65/91aee3e77757f106ac2055334a4b6521.jpg",
      "position": null,
      "small_url": "https://salt.tikicdn.com/cache/200x280/ts/product/22/66/65/91aee3e77757f106ac2055334a4b6521.jpg",
      "thumbnail_url": "https://salt.tikicdn.com/cache/200x280/ts/product/22/66/65/91aee3e77757f106ac2055334a4b6521.jpg"
    },
    {
      "base_url": "https://salt.tikicdn.com/ts/product/b9/66/db/a5176d1fa2a2c11b12e5ec68f08fb5e2.jpg",
      "is_gallery": true,
      "label": null,
      "large_url": "https://salt.tikicdn.com/cache/w1200/ts/product/b9/66/db/a5176d1fa2a2c11b12e5ec68f08fb5e2.jpg",
      "medium_url": "https://salt.tikicdn.com/cache/w300/ts/product/b9/66/db/a5176d1fa2a2c11b12e5ec68f08fb5e2.jpg",
      "position": null,
      "small_url": "https://salt.tikicdn.com/cache/200x280/ts/product/b9/66/db/a5176d1fa2a2c11b12e5ec68f08fb5e2.jpg",
      "thumbnail_url": "https://salt.tikicdn.com/cache/200x280/ts/product/b9/66/db/a5176d1fa2a2c11b12e5ec68f08fb5e2.jpg"
    }
  ],
  "warranty_policy": null,
  "authors": [
    {
      "id": 178323,
      "name": "Armand Mattelart",
      "slug": "armand-mattelart"
    },
    {
      "id": 178325,
      "name": "Michèle Mattelart",
      "slug": "michele-mattelart"
    }
  ],
  "current_seller": {
    "id": 1,
    "sku": "7722625516194",
    "name": "Tiki Trading",
    "link": "https://tiki.vn/cua-hang/tiki-trading",
    "logo": "d1/3f/ae/13ce3d83ab6b6c5e77e6377ad61dc4a5.jpg",
    "price": 141000,
    "product_id": "274763163",
    "store_id": 40395,
    "is_best_store": false,
    "is_offline_installment_supported": null
  },
  "other_sellers": [
    {
      "id": 7247,
      "name": "Alpha Books Official",
      "link": "https://tiki.vn/cua-hang/alphabooks-official",
      "logo": "https://vcdn.tikicdn.com/ts/seller/38/74/f3/f9cf41005697c643397d9b09d335f4c4.jpg",
      "price": 148000,
      "product_id": "275246402",
      "store_id": 7082
    }
  ],
  "specifications": [
    {
      "name": "Thông tin chung",
      "attributes": [
        {
          "code": "bookcare_service",
          "name": "Bookcare",
          "value": "Có"
        },
        {
          "code": "publisher_vn",
          "name": "Công ty phát hành",
          "value": "Viện IRED"
        },
        {
          "code": "publication_date",
          "name": "Ngày xuất bản",
          "value": "2024-04-01 00:00:00"
        },
        {
          "code": "dimensions",
          "name": "Kích thước",
          "value": "24x16 cm"
        },
        {
          "code": "dich_gia",
          "name": "Dịch Giả",
          "value": "Hồ Thị Hòa"
        },
        {
          "code": "book_cover",
          "name": "Loại bìa",
          "value": "Bìa mềm"
        },
        {
          "code": "number_of_page",
          "name": "Số trang",
          "value": "272"
        },
        {
          "code": "manufacturer",
          "name": "Nhà xuất bản",
          "value": "Nhà Xuất Bản Khoa Học Xã Hội"
        }
      ]
    }
  ],
  "price_comparison": {
    "sub_title": "Giá từ 148.000 ₫",
    "title": "So sánh 1 nhà bán khác"
  },
  "product_links": [],
  "gift_item_title": "0 quà tặng kèm",
  "services_and_promotions": [],
  "promitions": [],
  "stock_item": {
    "max_sale_qty": 1000,
    "min_sale_qty": 1,
    "preorder_date": null,
    "qty": 1000
  },
  "quantity_sold": {
    "text": "Đã bán 55",
    "value": 55
  },
  "categories": {
    "id": 9725,
    "name": "Lịch Sử Thế Giới",
    "is_leaf": true
  },
  "breadcrumbs": [
    {
      "url": "/nha-sach-tiki/c8322",
      "name": "Nhà Sách Tiki",
      "category_id": 8322
    },
    {
      "url": "/sach-truyen-tieng-viet/c316",
      "name": "Sách tiếng Việt",
      "category_id": 316
    },
    {
      "url": "/lich-su-dia-ly/c880",
      "name": "Sách Lịch sử",
      "category_id": 880
    },
    {
      "url": "/lich-su-the-gioi/c9725",
      "name": "Lịch Sử Thế Giới",
      "category_id": 9725
    },
    {
      "url": "https://tiki.vn/lich-su-cac-ly-thuyet-truyen-thong-p274763162.html",
      "name": "Lịch Sử Các Lý Thuyết Truyền Thông",
      "category_id": 0
    }
  ],
  "installment_info_v2": null,
  "installment_info_v3": [
    {
      "display_text": "Ưu đãi đến 600k với thẻ TikiCard",
      "icon": "https://salt.tikicdn.com/ts/upload/73/4d/f7/f86e767bffc14aa3d6abed348630100b.png",
      "summary": "Ưu đãi đến 600k với thẻ TikiCard.",
      "title": "Ưu đãi đến 600k với thẻ TikiCard",
      "type": "other",
      "url": "https://tiki.vn/san-pham-so/the-dong-thuong-hieu-tiki-co-card"
    },
    {
      "display_text": "Mua trước trả sau",
      "icon": "https://salt.tikicdn.com/ts/upload/2a/27/6a/7bbba1f6c93a1a42a3c314e7b5825f4c.png",
      "summary": "Duyệt hồ sơ nhanh chóng qua công ty tài chính.",
      "title": "Mua trước trả sau",
      "type": "postpaid",
      "url": "https://tiki.vn/mua-truoc-tra-sau/thanh-toan?src=pdp&masterId=274763162&pid=274763163&seller_id=1&qty=1"
    }
  ],
  "is_seller_in_chat_whitelist": true,
  "inventory": {
    "product_virtual_type": null,
    "fulfillment_type": "tiki_delivery"
  },
  "warranty_info": [],
  "return_and_exchange_policy": "Đổi trả trong<br><b>30 ngày</b><br>nếu sp lỗi.",
  "is_tier_pricing_available": false,
  "is_tier_pricing_eligible": false,
  "benefits": [
    {
      "icon": "https://salt.tikicdn.com/ts/upload/c5/37/ee/76c708d43e377343e82baee8a0340297.png",
      "text": "Được đồng kiểm khi nhận hàng"
    },
    {
      "icon": "https://salt.tikicdn.com/ts/upload/ea/02/b4/b024e431ec433e6c85d4734aaf35bd65.png",
      "text": "<b>Được hoàn tiền 200%</b> nếu là hàng giả."
    },
    {
      "icon": "https://salt.tikicdn.com/ts/upload/d8/c7/a5/1cd5bd2f27f9bd74b2c340b8e27c4d82.png",
      "text": "Đổi trả miễn phí trong 30 ngày. Được đổi ý.",
      "sub_text": [],
      "cta": {
        "text": "Chi tiết",
        "type": "open_policy_return_modal"
      }
    }
  ],
  "return_policy": {
    "body": [
      {
        "label": "",
        "content": [
          "Được đổi ý (sản phẩm phải còn nguyên hộp, tem, phụ kiện, chưa kích hoạt bảo hành, không áp dụng đơn hàng trả góp), hoặc",
          "Sản phẩm không đúng cam kết (lỗi kỹ thuật, giao sai/thiếu, bể vỡ…)"
        ]
      }
    ],
    "cta": {
      "link": "https://hotro.tiki.vn/s/article/chinh-sach-doi-tra-san-pham",
      "text_button": "Tìm hiểu thêm"
    },
    "title": "Đổi trả miễn phí trong 30 ngày"
  }
}