{
  "id": 199030585,
  "master_id": 199030585,
  "sku": "4506689738854",
  "name": "Search Inside Yourself – Tìm kiếm bên trong bạn (Tái bản)",
  "url_key": "search-inside-yourself-tim-kiem-ben-trong-ban-tai-ban-p199030585",
  "url_path": "search-inside-yourself-tim-kiem-ben-trong-ban-tai-ban-p199030585.html?spid=199030586",
  "short_url": "https://tiki.vn/product-p199030585.html?spid=199030586",
  "type": "simple",
  "book_cover": null,
  "short_description": "Tất cả chúng ta đều biết công cụ tìm kiếm Google và công ty Google với văn hóa doanh nghiệp tuyệt vời nổi tiếng khắp thế giới, nhưng liệu có bao nhiêu người trong số chúng ta biết được điều gì đã làm ...",
  "price": 109000,
  "list_price": 149000,
  "original_price": 149000,
  "badges": [
    {
      "code": "new_pdp",
      "text": "v1"
    }
  ],
  "badges_new": [
    {
      "placement": "left_brand",
      "code": "is_authentic",
      "type": "is_authentic",
      "index": 4,
      "icon": "https://salt.tikicdn.com/ts/upload/d7/56/04/b93b8c666e13f49971483596ef14800f.png",
      "icon_width": 89,
      "icon_height": 20,
      "text_color": null,
      "background_color": null,
      "href": null,
      "text": null
    },
    {
      "placement": "right_authentic",
      "code": "return_policy",
      "type": "return_policy",
      "index": 3,
      "icon": "https://salt.tikicdn.com/ts/ta/b1/3f/4e/cc3d0a2dd751a7b06dd97d868d6afa56.png",
      "icon_width": 114,
      "icon_height": 20,
      "text_color": null,
      "background_color": null,
      "href": null,
      "text": null
    }
  ],
  "badges_v3": [
    {
      "placement": "pdp_badge",
      "code": "return_policy",
      "type": "pdp_icon_badge",
      "index": 3,
      "icon": "https://salt.tikicdn.com/ts/ta/b1/3f/4e/cc3d0a2dd751a7b06dd97d868d6afa56.png",
      "icon_width": 114,
      "icon_height": 20,
      "text_color": null,
      "background_color": null,
      "href": null,
      "text": null
    },
    {
      "placement": "pdp_badge",
      "code": "is_authentic",
      "type": "pdp_icon_badge",
      "index": 4,
      "icon": "https://salt.tikicdn.com/ts/upload/d7/56/04/b93b8c666e13f49971483596ef14800f.png",
      "icon_width": 89,
      "icon_height": 20,
      "text_color": null,
      "background_color": null,
      "href": null,
      "text": null
    }
  ],
  "tracking_info": {
    "amplitude": {
      "is_authentic": true,
      "is_freeship_xtra": false,
      "is_hero": false,
      "is_top_brand": false,
      "return_reason": "any_reason"
    }
  },
  "discount": 40000,
  "discount_rate": 27,
  "rating_average": 4.7,
  "review_count": 101,
  "review_text": "(101)",
  "favourite_count": 0,
  "thumbnail_url": "https://salt.tikicdn.com/cache/280x280/ts/product/7e/90/12/c0a91ec408287e64e03611cc430f1318.jpg",
  "has_ebook": false,
  "inventory_status": "available",
  "inventory_type": "instock",
  "productset_group_name": "",
  "is_fresh": false,
  "seller": null,
  "is_flower": false,
  "has_buynow": true,
  "is_gift_card": false,
  "salable_type": null,
  "data_version": 3300,
  "day_ago_created": 942,
  "all_time_quantity_sold": 2187,
  "meta_title": "",
  "meta_description": "",
  "meta_keywords": "",
  "is_baby_milk": false,
  "is_acoholic_drink": false,
  "description": "<p>Tất cả chúng ta đều biết công cụ tìm kiếm Google và công ty Google với văn hóa doanh nghiệp tuyệt vời nổi tiếng khắp thế giới, nhưng liệu có bao nhiêu người trong số chúng ta biết được điều gì đã làm nên nền tảng cho sự nổi tiếng đó? Chade-Meng Tan – tác giả cuốn sách Search Inside Yourself sẽ giải thích cho bạn bí mật đó.</p>\n<p>Mỗi năm, có đến hàng nghìn kĩ sư Google tham gia một trong 12 khóa đào tạo về thiền để tăng cường khả năng “cân bằng nhận thức” về những gì đang diễn ra xung quanh. Khóa học nổi tiếng nhất – mang tên “Search inside yourself” (Tìm kiếm bên trong bạn) – luôn là khóa học được trông đợi nhất và thu hút nhiều người tham gia nhất với danh sách học viên chờ tham dự dài đến sáu tháng. Khóa học do Chade-Meng Tan khởi sướng, ông là người rất có ảnh hưởng đến văn hóa Google, là người mà bất cứ nhân vật nổi tiếng nào khi đến thăm công ty cũng đều muốn gặp. Tham vọng của Meng chính là: “Soi sáng tâm trí, mở rộng trái tim và tạo ra hòa bình thế giới”.</p>\n<p>Cuốn sách Search inside yourself đã được ông viết lại dựa trên các kinh nghiệm đúc kết từ khóa học cùng các bài tập thiền để mọi người trong chúng ta đều có thể áp dụng được mà không cần phải tham gia khóa học kia của Google. Bằng ngôn từ đơn giản, dễ hiểu, cùng các bước luyện tập cơ bản nhằm giúp con người kiểm soát trí thông minh cảm xúc – làm chủ được cảm xúc bản thân, từ đó trở thành con người hạnh phúc nhất thế giới và lan tỏa niềm vui đến mọi người. “Tôi không thích mang Phật giáo vào Google”, Meng nói. “Tôi thích giúp đỡ mọi người ở Goolge tìm kiếm chìa khóa hạnh phúc”.</p>\n<p>Đúng như Eric Schmidt, Giám đốc điều hành của Google đã từng nói: “Cuốn sách này và khóa học mà nó dựa trên đại diện cho một trong những khía cạnh tuyệt vời nhất của văn hóa Google – một cá nhân với một ý tưởng thật sự vĩ đại có thể thay đổi thế giới”.</p>\n<p>Cuốn sách được chia làm ba phần chính:</p>\n<p>• Rèn luyện khả năng chú ý: Chú ý là nền tảng của mọi năng lực cảm xúc và nhận thức cao hơn. Do đó, bất cứ giáo trình rèn luyện trí thông minh cảm xúc nào cũng đều phải bắt đầu với việc rèn luyện khả năng chú ý. Ý tưởng ở đây là rèn luyện khả năng chú ý để tạo ra một tâm trí vừa an bình vừa sáng sủa. Một tâm trí như vậy sẽ tạo nền tảng cho trí thông minh cảm xúc.</p>\n<p>• Tự phát triển kiến thức và tự làm chủ bản thân: Sử dụng khả năng chú ý đã qua rèn luyện để nâng cao khả năng nhận thức quá trình cảm giác và tư duy của bạn. Từ đó, bạn có thể quan sát ngày càng rõ ràng dòng suy nghĩ và quá trình cảm giác của mình, với sự khách quan như từ góc nhìn của một người thứ ba. Khi làm được như vậy, bạn sẽ tạo ra một loại kiến thức sâu sắc do bạn tự khám phá ra và loại kiến thức này cuối cùng sẽ dẫn đến sự tự làm chủ bản thân.</p>\n<p>• Tạo ra các thói quen hữu ích cho tâm: Hãy tưởng tượng rằng bất cứ khi nào bạn gặp ai đó, ý nghĩ đầu tiên, theo bản năng, theo thói quen của bạn là, tôi muốn người này được hạnh phúc. Có những thói quen như vậy sẽ thay đổi mọi thứ ở nơi làm việc, vì ý tốt chân thành này sẽ được người khác cảm nhận một cách vô thức, và tạo ra loại tin tưởng dẫn đến những sự hợp tác có hiệu quả cao. Những thói quen như vậy có thể được rèn luyện để trở thành tự nhiên.</p>\n<p>Mục lục:</p>\n<p>Những lời khen tặng</p>\n<p>Lời nói đầu</p>\n<p>Lời giới thiệu</p>\n<p>Mở đầu</p>\n<p>Chương 1: Thậm chí một kỹ sư cũng có thể thành công về trí thông minh cảm xúc<br />Chương 2: Hãy thở như thể cuộc đời bạn phụ thuộc vào nó<br />Chương 3: Thiền không ngồi trên đệm<br />Chươgn 4: Sự tự tin hữu cơ<br />Chương 5: Điều khiển cảm xúc như thuần dưỡng một con ngựa <br />Chương 6: Tạo ra lợi nhuận, vượt qua đại dương và thay đổi thế giới<br />Chương 7: Sự đồng cảm và điệu tango của bộ não<br />Chương 8: Vừa có hiệu quả, vừa được yêu quý<br />Chươgn 9: Ba bước dễ dàng để đi đến hòa bình thế giới<br />Lời kết: Cứu thế giới khi bạn rảnh<br />Lời cảm ơn</p>\n<p>Chú thích</p>\n<p>Danh sách tài liệu và sách hay nên đọc</p>\n<p>Thông tin tác giả:</p>\n<p>Chade-Meng Tan là chàng kĩ sư vui tính của Google (người không ai có thể phủ nhận được). Ông là một trong những kĩ sư đầu tiên của Google. Ông bắt đầu làm việc cho Google từ năm 2000 sau 5 năm cống hiến cho Kent Ridge Digital Laboratories ở Singapore. Tại Google, ông có 8 năm làm việc dưới chức danh kỹ sư cho một số dự án như tìm kiếm trên nền tảng di động.</p>\n<p>Công việc nền tảng di động. Công việc hiện tại của ông là “khai sáng trí óc, cởi mở tâm hồn và tọa ra sự yên bình”.</p>\n<p>Trích đoạn sách:</p>\n<p>Thậm chí một kỹ sư cũng có thể thành công về trí thông minh cảm xúc</p>\n<p>Tôi muốn bắt đầu chuyến hành trình của chúng ta bằng một tinh thần lạc quan, một phần là do nếu bắt đầu bằng một tinh thần bi quan thì sách còn lâu mới bán được. Quan trọng hơn, dựa trên những kinh nghiệm giảng dạy tại Google và các nơi khác mà nhóm của tôi có được thì tôi lạc quan rằng, trí thông minh cảm xúc là một trong những chỉ báo tốt nhất về thành công trong công việc cũng như sự thỏa mãn trong cuộc sống, và ai cũng có thể được đào tạo để sở hữu nó. Với sự đào tạo đúng, bất cứ ai cũng có thể trở nên thông minh hơn về mặt cảm xúc. Với tinh thần “nếu Meng có thể nấu ăn thì bạn cũng có thể”, nếu chương trình đào tạo này có tác dụng với một kỹ sư nghiêm túc và cực kỳ nội tâm như tôi, thì có lẽ nó sẽ có tác dụng với bạn.</p>\n<p>Định nghĩa chuẩn nhất về trí thông minh cảm xúc là của hai người được coi là cha đẻ của khung lý thuyết về trí thông minh cảm xúc, Peter Salovey và John D. Mayer. Họ định nghĩa trí thông minh cảm xúc như sau:</p>\n<p>Khả năng theo dõi cảm giác và cảm xúc của mình cũng như của người khác, phân biệt chúng, và sử dụng thông tin này để dẫn dắt tư duy và hành động của mình1.</p>\n<p>Cuốn sách đột phá khiến chủ đề này trở nên phổ biến là Emotional Intelligence: Why It Can Matter More Tan IQ (Trí tuệ xúc cảm) của Daniel Goleman, người bạn và cũng là người cố vấn của chúng tôi. Một trong những thông điệp quan trọng nhất của cuốn sách là năng lực cảm xúc không phải là bẩm sinh; chúng là những khả năng mà người ta có thể học hỏi được. Nói cách khác, bạn có thể chủ đích trang bị năng lực cảm xúc thông qua luyện tập. Goleman đã xây dựng một cấu trúc rất hữu ích về trí thông minh cảm xúc bằng cách phân loại nó thành năm phần. Đó là:</p>\n<p>1.Khả năng am hiểu bản thân: Kiến thức về các trạng thái bên trong, sở thích, nguồn lực, và trực giác của chính mình</p>\n<p>2. Khả năng kiểm soát bản thân: Khả năng quản lý các trạng thái bên trong, các xung động, và nguồn lực của chính mình</p>\n<p>3. Động lực: Những xu hướng cảm xúc dẫn dắt hoặc hỗ trợ việc đạt được mục tiêu</p>\n<p>4. Cảm thông: Khả năng am hiểu cảm xúc, nhu cầu và mối quan tâm của người khác</p>\n<p>5. Kỹ năng xã hội: Sự thành thạo trong việc gợi ra những phản ứng mong muốn bên trong người khác</p>\n<p>Salovey và Mayer không phải là những người duy nhất có công trình liên quan đến trí thông minh cảm xúc và xã hội. Ví dụ, Howard Gardner là người nổi tiếng vì đã đưa ra ý tưởng rằng có nhiều loại hình thông minh. Gardner cho rằng mọi người có thể thông minh theo những cách mà bài kiểm tra IQ không đo lường được. Ví dụ, một đứa trẻ có thể không giỏi làm toán, nhưng lại có năng khiếu về ngôn ngữ hoặc sáng tác nhạc, thì chúng ta nên coi cậu bé là thông minh. Gardner đã tạo ra một danh sách bảy loại hình thông minh (sau này tăng lên thành tám). Hai trong số đó, trí thông minh nội tâm cá nhân và trí thông minh tương tác cá nhân, có liên quan mật thiết đến trí thông minh cảm xúc. Gardner gọi chúng là “trí thông minh cá nhân”.</p>\n<p>Năm phần trí thông minh cảm xúc của Goleman vẽ ra rất đẹp con đường đi vào trí thông minh cá nhân của Gardner: bạn có thể coi ba phần trí thông minh cảm xúc đầu tiên là trí thông minh nội tâm cá nhân và hai phần sau là trí thông minh tương tác cá nhân.</p>\n<p>Tôi thấy khá buồn cười là minh họa tốt nhất về việc trí thông minh cảm xúc là một năng lực có thể học hỏi được không phải đến từ một bài viết mang tính học thuật mà đến từ câu chuyện về Ebenezer Scrooge trong A Christmas Carol2 (Giáng Sinh Yêu Tương). Ở phần đầu câu chuyện, Scrooge là một minh chứng về trí thông minh cảm xúc thấp. Trí thông minh nội tâm cá nhân của ông quá thấp, ông không thể tạo ra sự thỏa mãn về mặt cảm xúc cho chính mình dù ông rất giàu. Tực tế, ông am hiểu bản thân rất kém, phải cần đến ba con ma để giúp ông hiểu về bản thân mình. Tất nhiên, trí thông minh tương tác cá nhân của ông thì siêu tồi. Tuy nhiên, gần cuối câu chuyện, Scooge lại trở thành một ví dụ về trí thông minh cảm xúc cao. Ông đã phát triển khả năng am hiểu bản thân mạnh mẽ, có thể kiểm soát cảm xúc của mình, đồng thời các kỹ năng xã hội và khả năng cảm thông của ông cũng nở rộ. Scrooge là một minh chứng cho thấy trí thông minh cảm xúc là một thứ có thể được phát triển (trong phiên bản mà tôi xem, nó xuất hiện trong không gian của một bộ phim truyền hình dài hai tiếng với đủ thời gian dành cho quảng cáo, nhưng bản mà bạn xem có thể khác). Ở phần sau của cuốn sách này, chúng ta sẽ kiểm tra chi tiết sự phát triển của từng phần trí thông minh cảm xúc. Tật may là việc này sẽ không cần đến những con ma Giáng sinh.</p>\n<p>Những lợi ích của trí thông minh cảm xúc</p>\n<p>Có một câu hỏi quan trọng mà những người bạn của tôi trong lĩnh vực đào tạo gọi là câu hỏi thế thì sao, kiểu như, “Vâng, rất hay, nhưng thế thì trí thông minh cảm xúc có tác dụng gì cho tôi?”. Trong bối cảnh công sở, trí thông minh cảm xúc giúp trang bị ba bộ kỹ năng quan trọng: Hiệu suất làm việc nổi bật, năng lực lãnh đạo xuất sắc, và khả năng tạo ra các điều kiện cho hạnh phúc.</p>\n<p>Hiệu suất làm việc nổi bật</p>\n<p>Điều đầu tiên trí thông minh cảm xúc giúp trang bị là hiệu suất làm việc nổi bật. Các nghiên cứu đã cho thấy năng lực cảm xúc quan trọng gấp đôi chuyên môn và kiến thức thuần túy trong việc tạo ra sự hoàn hảo. Một nghiên cứu của Martin Seligman, người được coi là cha đẻ của tâm lý học tích cực hiện đại và cũng là người tạo ra ý tưởng rằng tính lạc quan có thể học hỏi được, đã cho thấy rằng các nhân viên bán bảo hiểm lạc quan bán được nhiều hơn các đồng nghiệp bi quan 8% trong năm đầu tiên và 31% trong năm thứ hai4. (Vâng, tôi lạc quan về việc viết ra một cuốn sách bán chạy nhất. Cám ơn vì bạn đã hỏi.) Tôi không ngạc nhiên về điều này. Suy cho cùng, có nhiều công việc trong ngành bán hàng và dịch vụ khách hàng mà các năng lực cảm xúc rõ ràng có khả năng tạo ra sự khác biệt lớn. Bằng trực giác, chúng ta đã biết điều này rồi. Điều khiến tôi ngạc nhiên là nó đúng thậm chí cả với những người làm việc trong khu vực kỹ thuật như những kỹ sư giống tôi, những người mà bạn sẽ nghĩ rằng thành công chỉ dựa vào trí thông minh thuần túy. Teo một nghiên cứu thì sáu năng lực đứng đầu giúp phân biệt những người làm việc hiệu suất cao với những người làm việc bình thường trong khu vực kỹ thuật là (theo thứ tự này):</p>\n<p>1. Khát khao đạt được thành tựu và tiêu chuẩn thành tựu cao<br />2. Khả năng gây ảnh hưởng<br />3. Tư duy khái niệm<br />4. Khả năng phân tích<br />5. Chủ động chấp nhận thử thách<br />6. Tự tin.</p>\n<p>Trong sáu năng lực này, chỉ có hai năng lực (khả năng phân tích và tư duy khái niệm) là những năng lực thuộc về trí thông minh thuần túy. Bốn năng lực kia, kể cả hai năng lực đứng đầu, là năng lực thuộc về cảm xúc.</p>\n<p>Trí thông minh cảm xúc cao có thể giúp bất kỳ ai trở nên xuất sắc trong công việc, thậm chí cả kỹ sư.</p><p>Giá sản phẩm trên Tiki đã bao gồm thuế theo luật hiện hành. Bên cạnh đó, tuỳ vào loại sản phẩm, hình thức và địa chỉ giao hàng mà có thể phát sinh thêm chi phí khác như phí vận chuyển, phụ phí hàng cồng kềnh, thuế nhập khẩu (đối với đơn hàng giao từ nước ngoài có giá trị trên 1 triệu đồng).....</p>",
  "images": [
    {
      "base_url": "https://salt.tikicdn.com/ts/product/7e/90/12/c0a91ec408287e64e03611cc430f1318.jpg",
      "is_gallery": true,
      "label": null,
      "large_url": "https://salt.tikicdn.com/cache/w1200/ts/product/7e/90/12/c0a91ec408287e64e03611cc430f1318.jpg",
      "medium_url": "https://salt.tikicdn.com/cache/w300/ts/product/7e/90/12/c0a91ec408287e64e03611cc430f1318.jpg",
      "position": null,
      "small_url": "https://salt.tikicdn.com/cache/200x280/ts/product/7e/90/12/c0a91ec408287e64e03611cc430f1318.jpg",
      "thumbnail_url": "https://salt.tikicdn.com/cache/200x280/ts/product/7e/90/12/c0a91ec408287e64e03611cc430f1318.jpg"
    },
    {
      "base_url": "https://salt.tikicdn.com/ts/product/5b/63/d1/39660d0bd5a7d51c277991c9991e5995.png",
      "is_gallery": true,
      "label": null,
      "large_url": "https://salt.tikicdn.com/cache/w1200/ts/product/5b/63/d1/39660d0bd5a7d51c277991c9991e5995.png",
      "medium_url": "https://salt.tikicdn.com/cache/w300/ts/product/5b/63/d1/39660d0bd5a7d51c277991c9991e5995.png",
      "position": null,
      "small_url": "https://salt.tikicdn.com/cache/200x280/ts/product/5b/63/d1/39660d0bd5a7d51c277991c9991e5995.png",
      "thumbnail_url": "https://salt.tikicdn.com/cache/200x280/ts/product/5b/63/d1/39660d0bd5a7d51c277991c9991e5995.png"
    },
    {
      "base_url": "https://salt.tikicdn.com/ts/product/bd/3f/81/681dad6dceb644f484e12aa902ab0a13.png",
      "is_gallery": true,
      "label": null,
      "large_url": "https://salt.tikicdn.com/cache/w1200/ts/product/bd/3f/81/681dad6dceb644f484e12aa902ab0a13.png",
      "medium_url": "https://salt.tikicdn.com/cache/w300/ts/product/bd/3f/81/681dad6dceb644f484e12aa902ab0a13.png",
      "position": null,
      "small_url": "https://salt.tikicdn.com/cache/200x280/ts/product/bd/3f/81/681dad6dceb644f484e12aa902ab0a13.png",
      "thumbnail_url": "https://salt.tikicdn.com/cache/200x280/ts/product/bd/3f/81/681dad6dceb644f484e12aa902ab0a13.png"
    }
  ],
  "warranty_policy": null,
  "authors": [
    {
      "id": 306173,
      "name": "Chade-Meng Tan",
      "slug": "chade-meng-tan"
    }
  ],
  "current_seller": {
    "id": 1,
    "sku": "2415027028367",
    "name": "Tiki Trading",
    "link": "https://tiki.vn/cua-hang/tiki-trading",
    "logo": "d1/3f/ae/13ce3d83ab6b6c5e77e6377ad61dc4a5.jpg",
    "price": 109000,
    "product_id": "199030586",
    "store_id": 40395,
    "is_best_store": false,
    "is_offline_installment_supported": null
  },
  "other_sellers": [
    {
      "id": 295057,
      "name": "HỆ THỐNG NHÀ SÁCH ABC",
      "link": "https://tiki.vn/cua-hang/he-thong-nha-sach-abc",
      "logo": "98/3d/ff/cec0ba0eaa575634616ab4605fccbe6d.jpg",
      "price": 149000,
      "product_id": "204421098",
      "store_id": 282399
    },
    {
      "id": 126688,
      "name": "info book",
      "link": "https://tiki.vn/cua-hang/info-book",
      "logo": "66/49/ce/c528ff3a6e4022b080c1f8c6fe7bc541.jpg",
      "price": 149000,
      "product_id": "206742517",
      "store_id": 117060
    },
    {
      "id": 97533,
      "name": "Nhà Sách Vĩnh Thụy",
      "link": "https://tiki.vn/cua-hang/nha-sach-vinh-thuy",
      "logo": "19/f2/bd/8bda12adffb15edf1b3d8339b0238283.jpg",
      "price": 149000,
      "product_id": "208913606",
      "store_id": 90454
    }
  ],
  "specifications": [
    {
      "name": "Thông tin chung",
      "attributes": [
        {
          "code": "book_version",
          "name": "Phiên bản sách",
          "value": "Phiên bản thường"
        },
        {
          "code": "publisher_vn",
          "name": "Công ty phát hành",
          "value": "Thái Hà"
        },
        {
          "code": "publication_date",
          "name": "Ngày xuất bản",
          "value": "2022-09-01 00:00:00"
        },
        {
          "code": "dimensions",
          "name": "Kích thước",
          "value": "15.5 x 22 cm"
        },
        {
          "code": "dich_gia",
          "name": "Dịch Giả",
          "value": "Kiều Anh Tú"
        },
        {
          "code": "book_cover",
          "name": "Loại bìa",
          "value": "Bìa mềm"
        },
        {
          "code": "number_of_page",
          "name": "Số trang",
          "value": "344"
        },
        {
          "code": "manufacturer",
          "name": "Nhà xuất bản",
          "value": "Nhà Xuất Bản Lao Động"
        }
      ]
    }
  ],
  "price_comparison": {
    "sub_title": "Giá từ 149.000 ₫",
    "title": "So sánh 3 nhà bán khác"
  },
  "product_links": [],
  "gift_item_title": "0 quà tặng kèm",
  "highlight": {
    "items": [
      "Rèn luyện khả năng chú ý, kiểm soát cảm xúc và tạo thói quen tâm.",
      "Tác giả là kỹ sư Google, mang đến kiến thức thực tế.",
      "Viết dễ hiểu, đi kèm bài tập thiền để áp dụng."
    ],
    "title": "Đặc điểm nổi bật"
  },
  "services_and_promotions": [],
  "promitions": [],
  "stock_item": {
    "max_sale_qty": 1000,
    "min_sale_qty": 1,
    "preorder_date": null,
    "qty": 1000
  },
  "quantity_sold": {
    "text": "Đã bán 2k",
    "value": 2187
  },
  "categories": {
    "id": 847,
    "name": "Bài học kinh doanh",
    "is_leaf": true
  },
  "breadcrumbs": [
    {
      "url": "/nha-sach-tiki/c8322",
      "name": "Nhà Sách Tiki",
      "category_id": 8322
    },
    {
      "url": "/sach-truyen-tieng-viet/c316",
      "name": "Sách tiếng Việt",
      "category_id": 316
    },
    {
      "url": "/sach-kinh-te/c846",
      "name": "Sách kinh tế",
      "category_id": 846
    },
    {
      "url": "/bai-hoc-kinh-doanh/c847",
      "name": "Bài học kinh doanh",
      "category_id": 847
    },
    {
      "url": "https://tiki.vn/search-inside-yourself-tim-kiem-ben-trong-ban-tai-ban-p199030585.html",
      "name": "Search Inside Yourself – Tìm kiếm bên trong bạn (Tái bản)",
      "category_id": 0
    }
  ],
  "installment_info_v2": null,
  "installment_info_v3": [
    {
      "display_text": "Ưu đãi đến 600k với thẻ TikiCard",
      "icon": "https://salt.tikicdn.com/ts/upload/73/4d/f7/f86e767bffc14aa3d6abed348630100b.png",
      "summary": "Ưu đãi đến 600k với thẻ TikiCard.",
      "title": "Ưu đãi đến 600k với thẻ TikiCard",
      "type": "other",
      "url": "https://tiki.vn/san-pham-so/the-dong-thuong-hieu-tiki-co-card"
    },
    {
      "display_text": "Mua trước trả sau",
      "icon": "https://salt.tikicdn.com/ts/upload/2a/27/6a/7bbba1f6c93a1a42a3c314e7b5825f4c.png",
      "summary": "Duyệt hồ sơ nhanh chóng qua công ty tài chính.",
      "title": "Mua trước trả sau",
      "type": "postpaid",
      "url": "https://tiki.vn/mua-truoc-tra-sau/thanh-toan?src=pdp&masterId=199030585&pid=199030586&seller_id=1&qty=1"
    }
  ],
  "is_seller_in_chat_whitelist": true,
  "inventory": {
    "product_virtual_type": null,
    "fulfillment_type": "tiki_delivery"
  },
  "warranty_info": [],
  "return_and_exchange_policy": "Đổi trả trong<br><b>30 ngày</b><br>nếu sp lỗi.",
  "is_tier_pricing_available": false,
  "is_tier_pricing_eligible": false,
  "benefits": [
    {
      "icon": "https://salt.tikicdn.com/ts/upload/c5/37/ee/76c708d43e377343e82baee8a0340297.png",
      "text": "Được đồng kiểm khi nhận hàng"
    },
    {
      "icon": "https://salt.tikicdn.com/ts/upload/ea/02/b4/b024e431ec433e6c85d4734aaf35bd65.png",
      "text": "<b>Được hoàn tiền 200%</b> nếu là hàng giả."
    },
    {
      "icon": "https://salt.tikicdn.com/ts/upload/d8/c7/a5/1cd5bd2f27f9bd74b2c340b8e27c4d82.png",
      "text": "Đổi trả miễn phí trong 30 ngày. Được đổi ý.",
      "sub_text": [],
      "cta": {
        "text": "Chi tiết",
        "type": "open_policy_return_modal"
      }
    }
  ],
  "return_policy": {
    "body": [
      {
        "label": "",
        "content": [
          "Được đổi ý (sản phẩm phải còn nguyên hộp, tem, phụ kiện, chưa kích hoạt bảo hành, không áp dụng đơn hàng trả góp), hoặc",
          "Sản phẩm không đúng cam kết (lỗi kỹ thuật, giao sai/thiếu, bể vỡ…)"
        ]
      }
    ],
    "cta": {
      "link": "https://hotro.tiki.vn/s/article/chinh-sach-doi-tra-san-pham",
      "text_button": "Tìm hiểu thêm"
    },
    "title": "Đổi trả miễn phí trong 30 ngày"
  }
}