{
  "id": 77109209,
  "master_id": 77109209,
  "sku": "2270954610737",
  "name": "Nghệ Thuật Đánh Cắp Ý Tưởng (10 Bí Mật Không Ai Nói Với Bạn Về Sáng Tạo)",
  "url_key": "nghe-thuat-danh-cap-y-tuong-10-bi-mat-khong-ai-noi-voi-ban-ve-sang-tao-p77109209",
  "url_path": "nghe-thuat-danh-cap-y-tuong-10-bi-mat-khong-ai-noi-voi-ban-ve-sang-tao-p77109209.html?spid=79449916",
  "short_url": "https://tiki.vn/product-p77109209.html?spid=79449916",
  "type": "simple",
  "book_cover": null,
  "short_description": "Cuốn sách gửi tới chúng ta thông điệp: thực tế là không có thứ gì trên đời là nguyên bản. Vậy nên hãy học hỏi từ các tác phẩm của người khác, phối lại, mường tượng lại và khám phá ra trên con đường ri...",
  "price": 84100,
  "list_price": 99000,
  "original_price": 99000,
  "badges": [
    {
      "code": "new_pdp",
      "text": "v1"
    }
  ],
  "badges_new": [
    {
      "placement": "left_brand",
      "code": "is_authentic",
      "type": "is_authentic",
      "index": 4,
      "icon": "https://salt.tikicdn.com/ts/upload/d7/56/04/b93b8c666e13f49971483596ef14800f.png",
      "icon_width": 89,
      "icon_height": 20,
      "text_color": null,
      "background_color": null,
      "href": null,
      "text": null
    },
    {
      "placement": "right_authentic",
      "code": "return_policy",
      "type": "return_policy",
      "index": 3,
      "icon": "https://salt.tikicdn.com/ts/ta/b1/3f/4e/cc3d0a2dd751a7b06dd97d868d6afa56.png",
      "icon_width": 114,
      "icon_height": 20,
      "text_color": null,
      "background_color": null,
      "href": null,
      "text": null
    }
  ],
  "badges_v3": [
    {
      "placement": "pdp_badge",
      "code": "return_policy",
      "type": "pdp_icon_badge",
      "index": 3,
      "icon": "https://salt.tikicdn.com/ts/ta/b1/3f/4e/cc3d0a2dd751a7b06dd97d868d6afa56.png",
      "icon_width": 114,
      "icon_height": 20,
      "text_color": null,
      "background_color": null,
      "href": null,
      "text": null
    },
    {
      "placement": "pdp_badge",
      "code": "is_authentic",
      "type": "pdp_icon_badge",
      "index": 4,
      "icon": "https://salt.tikicdn.com/ts/upload/d7/56/04/b93b8c666e13f49971483596ef14800f.png",
      "icon_width": 89,
      "icon_height": 20,
      "text_color": null,
      "background_color": null,
      "href": null,
      "text": null
    }
  ],
  "tracking_info": {
    "amplitude": {
      "is_authentic": true,
      "is_freeship_xtra": false,
      "is_hero": false,
      "is_top_brand": true,
      "return_reason": "any_reason"
    }
  },
  "discount": 14900,
  "discount_rate": 15,
  "rating_average": 5,
  "review_count": 56,
  "review_text": "(56)",
  "favourite_count": 0,
  "thumbnail_url": "https://salt.tikicdn.com/cache/280x280/ts/product/26/c0/cf/1168c09310cc601c82752f82b961cd78.jpg",
  "has_ebook": false,
  "inventory_status": "available",
  "inventory_type": "backorder",
  "productset_group_name": "",
  "is_fresh": false,
  "seller": null,
  "is_flower": false,
  "has_buynow": true,
  "is_gift_card": false,
  "salable_type": null,
  "data_version": 3300,
  "day_ago_created": 1547,
  "all_time_quantity_sold": 295,
  "meta_title": "",
  "meta_description": "",
  "meta_keywords": "",
  "is_baby_milk": false,
  "is_acoholic_drink": false,
  "description": "<p>Cuốn sách gửi tới chúng ta thông điệp: thực tế là không có thứ gì trên đời là nguyên bản. Vậy nên hãy học hỏi từ các tác phẩm của người khác, phối lại, mường tượng lại và khám phá ra trên con đường riêng của bạn. Hãy cứ dành thời gian cho những việc bạn thích làm, đôi khi những điều ban đầu chỉ là sở thích lại trở thành công việc bạn sẽ đeo đuổi suốt đời. Hãy cứ viết cuốn sách mà bạn muốn đọc, sản xuất bộ phim mà bạn muốn xem.</p>\n<p>Như Nhà thiết kế Tạ Quốc Kỳ Nam cũng đã viết trong lời giới thiệu cuốn sách: “Sáng tạo là gì?”, “ranh giới giữa tìm cảm hứng và đạo nhái?”, “làm sao để làm tốt hơn việc mình đang làm?” và “ý tưởng đến từ đâu?”… Người ta kiếm rất nhiều tiền từ việc trả lời những câu hỏi này qua những khoá học, workshop, sách self-help… Nhưng cuốn sách này sẽ khiến bạn ngưng làm mình mệt mỏi với các câu hỏi sáo mòn ấy và đưa bạn đến bước tiếp theo hiệu quả hơn: bắt đầu “đánh cắp” những điều hay ho như cách những người bạn thần tượng làm nên sự nghiệp của họ, và bạn sẽ làm chuyện ấy tỉnh táo và bài bản – như một nghệ sĩ.”</p>\n<p>TRÍCH CÁC Ý KIẾN</p>\n<p>“Austin Kleon thực sự là một torng những người thú vị nhất trên Internet… Anh ấy đã đưa ra một ví dụ rõ ràng và hấp dẫn về khả năng sáng tạo bằng cách tổng hợp, cũng như vai trò của việc phối lại trong nền kinh tế ý tưởng” – The Atlantic</p>\n<p>- “Đầy ắp những lời khuyên có cơ sở áp dụng cho hầu hết mọi công việc” - Tạp chí School Libar</p>\n<p>- “Lỗi lạc, chân thực, và chính xác” - Rosame Cash</p>\n<p>MỘT SỐ ĐOẠN TRÍCH</p>\n<p>- “Thứ mà chúng ta nhìn được trong bất kỳ tác phẩm nghệ thuật nào chính là sự đấu tranh của người nghệ sỹ với chính giới hạn họ đặt ra.”</p>\n<p>- “ Điều làm chúng ta thú vị không chỉ là những thứ mà ta đã trải nghiệm mà còn là những điều ta chưa thử qua. Điều này cũng áp dụng trong công việc của bạn: Bạn phải biết đón nhận những giới hạn mình đặt ra và bước tiếp. Vì cuối cùng sự sáng tạo không chỉ là những thứ chúng ta chọn để thể hiện, nó còn là những gì chúng ta chọn để bỏ ra.Vậy nên hãy chọn một cách khôn ngoan.”</p>\n<p>- “Trong thời đại bùng nổ thông tin, những người có thể thăng tiến là những người biết phải bỏ qua việc gì, để có thể tập trung vào những việc quan trọng hơn. Không gì gây tê liệt hơn ý nghĩ rằng mọi khả năng đều khả thi. Cho rằng mình có thể làm được mọi thứ là một suy nghĩ đáng sợ.”</p>\n<p>- “Thiết lập và duy trì một nhịp sinh hoạt thậm chí còn quan trọng hơn là có quá nhiều thời gian. Sự trì trệ sẽ giết chết sáng tạo. Bạn phải luôn giữ nhịp điệu. Khi bạn lạc khỏi nhịp điệu đó, bạn sẽ sợ phải quay lại làm việc, bởi bạn biết nó sẽ rất tệ lúc khởi động lại – cho đến khi bạn lấy lại được thời gian biểu cũ.”</p>\n<p>- “Vấn đề với những sản phẩm sáng tạo là: Đôi khi đến lúc mà mọi người nhận ra giá trị thực sự của những thứ bạn làm ra thì, có lẽ a) bạn đã phát ngán về nó rồi, hoặc b) bạn đã qua đời. Bạn không thể cứ đi tìm sự công nhận từ bên ngoài. Một khi bạn đưa tác phẩm của mình ra thế giới, bạn không thể nào kiểm soát được cách mọi người sẽ phản ứng và nhìn nhận nó.”</p>\n<p>-“Tất cả những gì bạn cần là một chút không gian và một chút thời gian – một nơi để làm việc, với một khoảng thời gian để làm nó; một chút cô đơn tự thân và một chút giam hãm tạm thời. Nếu điều kiện sống của bạn không cho phép điều đó, đôi khi bạn có thể tìm thấy một chút cô độc trong thiên nhiên.”</p>\n<p><strong>VỀ TÁC GIẢ:</strong></p>\n<p>Sách của tác giả Austin Kleon. Ông là nhà văn, và nghệ sĩ sống tại Austin, Texas, là tác giả của 3 cuốn sách bán chạy trên New York Times : Nghệ thuật « đánh cắp » ý tưởng ; Nghệ thuật PR bản thân ; Cứ làm đi và Newspaper Blackout<br /><br /></p><p>Giá sản phẩm trên Tiki đã bao gồm thuế theo luật hiện hành. Bên cạnh đó, tuỳ vào loại sản phẩm, hình thức và địa chỉ giao hàng mà có thể phát sinh thêm chi phí khác như phí vận chuyển, phụ phí hàng cồng kềnh, thuế nhập khẩu (đối với đơn hàng giao từ nước ngoài có giá trị trên 1 triệu đồng).....</p>",
  "images": [
    {
      "base_url": "https://salt.tikicdn.com/ts/product/26/c0/cf/1168c09310cc601c82752f82b961cd78.jpg",
      "is_gallery": true,
      "label": null,
      "large_url": "https://salt.tikicdn.com/cache/w1200/ts/product/26/c0/cf/1168c09310cc601c82752f82b961cd78.jpg",
      "medium_url": "https://salt.tikicdn.com/cache/w300/ts/product/26/c0/cf/1168c09310cc601c82752f82b961cd78.jpg",
      "position": null,
      "small_url": "https://salt.tikicdn.com/cache/200x280/ts/product/26/c0/cf/1168c09310cc601c82752f82b961cd78.jpg",
      "thumbnail_url": "https://salt.tikicdn.com/cache/200x280/ts/product/26/c0/cf/1168c09310cc601c82752f82b961cd78.jpg"
    },
    {
      "base_url": "https://salt.tikicdn.com/ts/product/82/e6/3a/5af6a7b80dfffa6f47f80420567c3743.jpg",
      "is_gallery": true,
      "label": null,
      "large_url": "https://salt.tikicdn.com/cache/w1200/ts/product/82/e6/3a/5af6a7b80dfffa6f47f80420567c3743.jpg",
      "medium_url": "https://salt.tikicdn.com/cache/w300/ts/product/82/e6/3a/5af6a7b80dfffa6f47f80420567c3743.jpg",
      "position": null,
      "small_url": "https://salt.tikicdn.com/cache/200x280/ts/product/82/e6/3a/5af6a7b80dfffa6f47f80420567c3743.jpg",
      "thumbnail_url": "https://salt.tikicdn.com/cache/200x280/ts/product/82/e6/3a/5af6a7b80dfffa6f47f80420567c3743.jpg"
    },
    {
      "base_url": "https://salt.tikicdn.com/ts/product/1c/09/5b/ea09ccbbf4679a268836cf38a1979b90.jpg",
      "is_gallery": true,
      "label": null,
      "large_url": "https://salt.tikicdn.com/cache/w1200/ts/product/1c/09/5b/ea09ccbbf4679a268836cf38a1979b90.jpg",
      "medium_url": "https://salt.tikicdn.com/cache/w300/ts/product/1c/09/5b/ea09ccbbf4679a268836cf38a1979b90.jpg",
      "position": null,
      "small_url": "https://salt.tikicdn.com/cache/200x280/ts/product/1c/09/5b/ea09ccbbf4679a268836cf38a1979b90.jpg",
      "thumbnail_url": "https://salt.tikicdn.com/cache/200x280/ts/product/1c/09/5b/ea09ccbbf4679a268836cf38a1979b90.jpg"
    },
    {
      "base_url": "https://salt.tikicdn.com/ts/product/f1/b6/17/23323255eb39e9336448be36573f3867.jpg",
      "is_gallery": true,
      "label": null,
      "large_url": "https://salt.tikicdn.com/cache/w1200/ts/product/f1/b6/17/23323255eb39e9336448be36573f3867.jpg",
      "medium_url": "https://salt.tikicdn.com/cache/w300/ts/product/f1/b6/17/23323255eb39e9336448be36573f3867.jpg",
      "position": null,
      "small_url": "https://salt.tikicdn.com/cache/200x280/ts/product/f1/b6/17/23323255eb39e9336448be36573f3867.jpg",
      "thumbnail_url": "https://salt.tikicdn.com/cache/200x280/ts/product/f1/b6/17/23323255eb39e9336448be36573f3867.jpg"
    },
    {
      "base_url": "https://salt.tikicdn.com/ts/product/7a/24/b2/e600b9cfa776d394425c6b115a3a18dd.jpg",
      "is_gallery": true,
      "label": null,
      "large_url": "https://salt.tikicdn.com/cache/w1200/ts/product/7a/24/b2/e600b9cfa776d394425c6b115a3a18dd.jpg",
      "medium_url": "https://salt.tikicdn.com/cache/w300/ts/product/7a/24/b2/e600b9cfa776d394425c6b115a3a18dd.jpg",
      "position": null,
      "small_url": "https://salt.tikicdn.com/cache/200x280/ts/product/7a/24/b2/e600b9cfa776d394425c6b115a3a18dd.jpg",
      "thumbnail_url": "https://salt.tikicdn.com/cache/200x280/ts/product/7a/24/b2/e600b9cfa776d394425c6b115a3a18dd.jpg"
    },
    {
      "base_url": "https://salt.tikicdn.com/ts/product/86/dc/19/fb683faf1a4d3a4530eb0cf6e30948c9.jpg",
      "is_gallery": true,
      "label": null,
      "large_url": "https://salt.tikicdn.com/cache/w1200/ts/product/86/dc/19/fb683faf1a4d3a4530eb0cf6e30948c9.jpg",
      "medium_url": "https://salt.tikicdn.com/cache/w300/ts/product/86/dc/19/fb683faf1a4d3a4530eb0cf6e30948c9.jpg",
      "position": null,
      "small_url": "https://salt.tikicdn.com/cache/200x280/ts/product/86/dc/19/fb683faf1a4d3a4530eb0cf6e30948c9.jpg",
      "thumbnail_url": "https://salt.tikicdn.com/cache/200x280/ts/product/86/dc/19/fb683faf1a4d3a4530eb0cf6e30948c9.jpg"
    },
    {
      "base_url": "https://salt.tikicdn.com/ts/product/3c/62/b3/8e130156d3302e48a6c53b6221250663.jpg",
      "is_gallery": true,
      "label": null,
      "large_url": "https://salt.tikicdn.com/cache/w1200/ts/product/3c/62/b3/8e130156d3302e48a6c53b6221250663.jpg",
      "medium_url": "https://salt.tikicdn.com/cache/w300/ts/product/3c/62/b3/8e130156d3302e48a6c53b6221250663.jpg",
      "position": null,
      "small_url": "https://salt.tikicdn.com/cache/200x280/ts/product/3c/62/b3/8e130156d3302e48a6c53b6221250663.jpg",
      "thumbnail_url": "https://salt.tikicdn.com/cache/200x280/ts/product/3c/62/b3/8e130156d3302e48a6c53b6221250663.jpg"
    },
    {
      "base_url": "https://salt.tikicdn.com/ts/product/7d/f4/3a/92e38805db9592f24025891de3fec53e.jpg",
      "is_gallery": true,
      "label": null,
      "large_url": "https://salt.tikicdn.com/cache/w1200/ts/product/7d/f4/3a/92e38805db9592f24025891de3fec53e.jpg",
      "medium_url": "https://salt.tikicdn.com/cache/w300/ts/product/7d/f4/3a/92e38805db9592f24025891de3fec53e.jpg",
      "position": null,
      "small_url": "https://salt.tikicdn.com/cache/200x280/ts/product/7d/f4/3a/92e38805db9592f24025891de3fec53e.jpg",
      "thumbnail_url": "https://salt.tikicdn.com/cache/200x280/ts/product/7d/f4/3a/92e38805db9592f24025891de3fec53e.jpg"
    },
    {
      "base_url": "https://salt.tikicdn.com/ts/product/30/41/85/6c7ce20f235a8f5d2d0aa1340d419229.jpg",
      "is_gallery": true,
      "label": null,
      "large_url": "https://salt.tikicdn.com/cache/w1200/ts/product/30/41/85/6c7ce20f235a8f5d2d0aa1340d419229.jpg",
      "medium_url": "https://salt.tikicdn.com/cache/w300/ts/product/30/41/85/6c7ce20f235a8f5d2d0aa1340d419229.jpg",
      "position": null,
      "small_url": "https://salt.tikicdn.com/cache/200x280/ts/product/30/41/85/6c7ce20f235a8f5d2d0aa1340d419229.jpg",
      "thumbnail_url": "https://salt.tikicdn.com/cache/200x280/ts/product/30/41/85/6c7ce20f235a8f5d2d0aa1340d419229.jpg"
    }
  ],
  "warranty_policy": null,
  "authors": [
    {
      "id": 16381,
      "name": "Austin Kleon",
      "slug": "austin-kleon"
    }
  ],
  "current_seller": {
    "id": 53660,
    "sku": "1755526302070",
    "name": "Nhà sách Fahasa",
    "link": "https://tiki.vn/cua-hang/nha-sach-fahasa",
    "logo": "f8/86/c0/12f7213bcdfd4d9a7a52e9b3a6704493.jpg",
    "price": 84100,
    "product_id": "79449916",
    "store_id": 51001,
    "is_best_store": false,
    "is_offline_installment_supported": null
  },
  "other_sellers": [
    {
      "id": 1,
      "name": "Tiki Trading",
      "link": "https://tiki.vn/cua-hang/tiki-trading",
      "logo": "d1/3f/ae/13ce3d83ab6b6c5e77e6377ad61dc4a5.jpg",
      "price": 66100,
      "product_id": "77109210",
      "store_id": 40395
    },
    {
      "id": 7247,
      "name": "Alpha Books Official",
      "link": "https://tiki.vn/cua-hang/alphabooks-official",
      "logo": "38/74/f3/f9cf41005697c643397d9b09d335f4c4.jpg",
      "price": 79000,
      "product_id": "77150385",
      "store_id": 7082
    },
    {
      "id": 111899,
      "name": "Sống Official",
      "link": "https://tiki.vn/cua-hang/abcbooks",
      "logo": "15/9e/ba/9e738b2510a755e5f27423ffb62aa0c7.jpg",
      "price": 79000,
      "product_id": "77186711",
      "store_id": 103533
    },
    {
      "id": 82087,
      "name": "Nhà Sách Lifebooks",
      "link": "https://tiki.vn/cua-hang/nha-sach-lifebooks",
      "logo": "a3/c9/64/eb97a5bb8c46816ff6c09027f1e1bb9a.jpg",
      "price": 79200,
      "product_id": "88933447",
      "store_id": 76421
    },
    {
      "id": 146243,
      "name": "ETS Books",
      "link": "https://tiki.vn/cua-hang/ets-books",
      "logo": "51/c9/eb/26acdd373eb04d0fce52f926dad2f725.jpg",
      "price": 79000,
      "product_id": "88949725",
      "store_id": 134929
    },
    {
      "id": 145814,
      "name": "Omega Plus Books",
      "link": "https://tiki.vn/cua-hang/omega-plus-books",
      "logo": "8b/17/0b/9e986158bc230b4fd699f07095893546.jpg",
      "price": 79000,
      "product_id": "88962434",
      "store_id": 134535
    },
    {
      "id": 126688,
      "name": "info book",
      "link": "https://tiki.vn/cua-hang/info-book",
      "logo": "66/49/ce/c528ff3a6e4022b080c1f8c6fe7bc541.jpg",
      "price": 99000,
      "product_id": "117892553",
      "store_id": 117060
    },
    {
      "id": 97533,
      "name": "Nhà Sách Vĩnh Thụy",
      "link": "https://tiki.vn/cua-hang/nha-sach-vinh-thuy",
      "logo": "19/f2/bd/8bda12adffb15edf1b3d8339b0238283.jpg",
      "price": 99000,
      "product_id": "120227740",
      "store_id": 90454
    },
    {
      "id": 295057,
      "name": "HỆ THỐNG NHÀ SÁCH ABC",
      "link": "https://tiki.vn/cua-hang/he-thong-nha-sach-abc",
      "logo": "98/3d/ff/cec0ba0eaa575634616ab4605fccbe6d.jpg",
      "price": 99000,
      "product_id": "192304502",
      "store_id": 282399
    },
    {
      "id": 259784,
      "name": "Bảo Châu Books",
      "link": "https://tiki.vn/cua-hang/bao-chau-books",
      "logo": "https://vcdn.tikicdn.com/ts/seller/3e/6e/38/a966cdb8129618eb7094498d4da28f86.jpg",
      "price": 99000,
      "product_id": "253137801",
      "store_id": 246822
    },
    {
      "id": 53179,
      "name": "Nhà sách PLV",
      "link": "https://tiki.vn/cua-hang/nha-sach-plv",
      "logo": "6e/20/ad/edbf695d6497987e535b42040ab1bb28.png",
      "price": 89000,
      "product_id": "274765357",
      "store_id": 50589
    }
  ],
  "specifications": [
    {
      "name": "Thông tin chung",
      "attributes": [
        {
          "code": "publisher_vn",
          "name": "Công ty phát hành",
          "value": "Alphabooks"
        },
        {
          "code": "publication_date",
          "name": "Ngày xuất bản",
          "value": "2021-02-01 00:00:00"
        },
        {
          "code": "dimensions",
          "name": "Kích thước",
          "value": "15 x 15 cm"
        },
        {
          "code": "dich_gia",
          "name": "Dịch Giả",
          "value": "Tô Duy"
        },
        {
          "code": "book_cover",
          "name": "Loại bìa",
          "value": "Bìa mềm"
        },
        {
          "code": "number_of_page",
          "name": "Số trang",
          "value": "160"
        },
        {
          "code": "seller_delivery_method",
          "name": "Phương thức giao hàng Seller Delivery",
          "value": "Nhà bán giao hàng cho khách hàng"
        },
        {
          "code": "manufacturer",
          "name": "Nhà xuất bản",
          "value": "Nhà Xuất Bản Thế Giới"
        }
      ]
    }
  ],
  "price_comparison": {
    "sub_title": "Giá từ 66.100 ₫",
    "title": "So sánh 11 nhà bán khác"
  },
  "product_links": [],
  "gift_item_title": "0 quà tặng kèm",
  "highlight": {
    "items": [
      "Hướng dẫn cách sáng tạo từ nguồn cảm hứng của người khác.",
      "Thông điệp thực tế và chân thực về quá trình sáng tạo.",
      "Kích thước nhỏ gọn, dễ mang theo và tham khảo."
    ],
    "title": "Đặc điểm nổi bật"
  },
  "services_and_promotions": [],
  "promitions": [],
  "stock_item": {
    "max_sale_qty": 1000,
    "min_sale_qty": 1,
    "preorder_date": null,
    "qty": 1000
  },
  "quantity_sold": {
    "text": "Đã bán 295",
    "value": 295
  },
  "categories": {
    "id": 385,
    "name": "Sách kỹ năng làm việc",
    "is_leaf": true
  },
  "breadcrumbs": [
    {
      "url": "/nha-sach-tiki/c8322",
      "name": "Nhà Sách Tiki",
      "category_id": 8322
    },
    {
      "url": "/sach-truyen-tieng-viet/c316",
      "name": "Sách tiếng Việt",
      "category_id": 316
    },
    {
      "url": "/sach-kinh-te/c846",
      "name": "Sách kinh tế",
      "category_id": 846
    },
    {
      "url": "/sach-ky-nang-lam-viec/c385",
      "name": "Sách kỹ năng làm việc",
      "category_id": 385
    },
    {
      "url": "https://tiki.vn/nghe-thuat-danh-cap-y-tuong-10-bi-mat-khong-ai-noi-voi-ban-ve-sang-tao-p77109209.html",
      "name": "Nghệ Thuật Đánh Cắp Ý Tưởng (10 Bí Mật Không Ai Nói Với Bạn Về Sáng Tạo)",
      "category_id": 0
    }
  ],
  "installment_info_v2": null,
  "installment_info_v3": [
    {
      "display_text": "Ưu đãi đến 600k với thẻ TikiCard",
      "icon": "https://salt.tikicdn.com/ts/upload/73/4d/f7/f86e767bffc14aa3d6abed348630100b.png",
      "summary": "Ưu đãi đến 600k với thẻ TikiCard.",
      "title": "Ưu đãi đến 600k với thẻ TikiCard",
      "type": "other",
      "url": "https://tiki.vn/san-pham-so/the-dong-thuong-hieu-tiki-co-card"
    },
    {
      "display_text": "Mua trước trả sau",
      "icon": "https://salt.tikicdn.com/ts/upload/2a/27/6a/7bbba1f6c93a1a42a3c314e7b5825f4c.png",
      "summary": "Duyệt hồ sơ nhanh chóng qua công ty tài chính.",
      "title": "Mua trước trả sau",
      "type": "postpaid",
      "url": "https://tiki.vn/mua-truoc-tra-sau/thanh-toan?src=pdp&masterId=77109209&pid=79449916&seller_id=53660&qty=1"
    }
  ],
  "is_seller_in_chat_whitelist": true,
  "inventory": {
    "product_virtual_type": null,
    "fulfillment_type": "seller_delivery"
  },
  "warranty_info": [],
  "return_and_exchange_policy": "Đổi trả trong<br><b>30 ngày</b><br>nếu sp lỗi.",
  "is_tier_pricing_available": false,
  "is_tier_pricing_eligible": false,
  "benefits": [
    {
      "icon": "https://salt.tikicdn.com/ts/upload/c5/37/ee/76c708d43e377343e82baee8a0340297.png",
      "text": "Được đồng kiểm khi nhận hàng"
    },
    {
      "icon": "https://salt.tikicdn.com/ts/upload/ea/02/b4/b024e431ec433e6c85d4734aaf35bd65.png",
      "text": "<b>Được hoàn tiền 200%</b> nếu là hàng giả."
    },
    {
      "icon": "https://salt.tikicdn.com/ts/upload/d8/c7/a5/1cd5bd2f27f9bd74b2c340b8e27c4d82.png",
      "text": "Đổi trả miễn phí trong 30 ngày. Được đổi ý.",
      "sub_text": [],
      "cta": {
        "text": "Chi tiết",
        "type": "open_policy_return_modal"
      }
    }
  ],
  "return_policy": {
    "body": [
      {
        "label": "",
        "content": [
          "Được đổi ý (sản phẩm phải còn nguyên hộp, tem, phụ kiện, chưa kích hoạt bảo hành, không áp dụng đơn hàng trả góp), hoặc",
          "Sản phẩm không đúng cam kết (lỗi kỹ thuật, giao sai/thiếu, bể vỡ…)"
        ]
      }
    ],
    "cta": {
      "link": "https://hotro.tiki.vn/s/article/chinh-sach-doi-tra-san-pham",
      "text_button": "Tìm hiểu thêm"
    },
    "title": "Đổi trả miễn phí trong 30 ngày"
  }
}